web3morebundlers/__init__.py
web3morebundlers/bundlers_middleware.py
web3morebundlers/bundlers_provider.py
web3morebundlers-0.1.1.dist-info/LICENSE
web3morebundlers-0.1.1.dist-info/METADATA
web3morebundlers-0.1.1.dist-info/WHEEL
web3morebundlers-0.1.1.dist-info/RECORD
