Metadata-Version: 2.1
Name: web3morebundlers
Version: 0.1.1
Summary: Superset of Flashbots' plugin for Web3.py allowing bundles to be submitted to many miners.
License: MIT
Author: Vile
Author-email: 111662603+vile@users.noreply.github.com
Requires-Python: >=3.9,<4.0
Classifier: License :: OSI Approved :: MIT License
Classifier: Programming Language :: Python :: 3
Classifier: Programming Language :: Python :: 3.9
Classifier: Programming Language :: Python :: 3.10
Classifier: Programming Language :: Python :: 3.11
Classifier: Programming Language :: Python :: 3.12
Requires-Dist: flashbots (>=1.1.1,<2.0.0)
Requires-Dist: web3 (>=5.22.0,<6.0.0)
